Workbook

Sheet Datos Crudos
A1: SENA — Análisis y Desarrollo de Software | Supermercado La Esquina
A2: HOJA 1: Datos Crudos — Dataset de Participantes
A3: ID | B3: Participante | C3: Rol | D3: Funcionalidad Prioritaria | E3: Ventas/Día | F3: ¿Facturación Electrónica? | G3: Tiempo Atención (min) | H3: Usa Tecnología
A4: 1 | B4: Carlos R. | C4: Dueño | D4: Control de inventario | E4: 50 | F4: Sí | G4: 4.5 | H4: Poco cómodo
A5: 2 | B5: Martha R. | C5: Cajera | D5: Registro de ventas | E5: 50 | F5: No sé | G5: 3 | H5: Cómodo
A6: 3 | B6: Julián P. | C6: Empleado | D6: Registro de ventas | E6: 50 | F6: No me importa | G6: 3.5 | H6: Cómodo
A7: 4 | B7: Cliente 1 | C7: Cliente | D7: Ver precios en pantalla | E7: - | F7: Sí | G7: - | H7: Muy cómodo
A8: 5 | B8: Cliente 2 | C8: Cliente | D8: Pago con tarjeta | E8: - | F8: Sí | G8: - | H8: Muy cómodo
A9: 6 | B9: Ana G. | C9: Cajera | D9: Registro de ventas | E9: 50 | F9: No | G9: 3.8 | H9: Cómodo
A10: 7 | B10: Pedro M. | C10: Empleado | D10: Control de inventario | E10: 50 | F10: No sé | G10: 4 | H10: Poco cómodo
A11: 8 | B11: Cliente 3 | C11: Cliente | D11: Ver precios en pantalla | E11: - | F11: Sí | G11: - | H11: Muy cómodo

Sheet Frecuencias y Estadísticas
A1: HOJA 2: Tablas de Frecuencias y Estadísticas
A3: TABLA 1 — Frecuencia de Funcionalidades Prioritarias
A4: Funcionalidad | B4: Frecuencia Absoluta | C4: Frecuencia Relativa (%) | D4: Prioridad
A5: Registro de ventas | B5: 3 | C5: =B5/SUM($B$5:$B$8)*100 -> 37.5 | D5: Alta
A6: Control de inventario | B6: 2 | C6: =B6/SUM($B$5:$B$8)*100 -> 25 | D6: Alta
A7: Ver precios en pantalla | B7: 2 | C7: =B7/SUM($B$5:$B$8)*100 -> 25 | D7: Media
A8: Pago con tarjeta | B8: 1 | C8: =B8/SUM($B$5:$B$8)*100 -> 12.5 | D8: Baja
A9: TOTAL | B9: =SUM(B5:B8) -> 8 | C9: =SUM(C5:C8) -> 100
A11: TABLA 2 — Opinión sobre Facturación Electrónica
A12: Respuesta | B12: Frecuencia | C12: Porcentaje (%)
A13: Sí | B13: 4 | C13: =B13/SUM($B$13:$B$15)*100 -> 57.142857
A14: No | B14: 1 | C14: =B14/SUM($B$13:$B$15)*100 -> 14.285714
A15: No sé / No importa | B15: 2 | C15: =B15/SUM($B$13:$B$15)*100 -> 28.571429
A16: TOTAL | B16: =SUM(B13:B15) -> 7 | C16: =SUM(C13:C15) -> 100
A18: TABLA 3 — Estadísticas de Ventas Diarias (participantes con dato numérico)
A19: Estadístico | B19: Valor | C19: Interpretación para el sistema
A20: Promedio de ventas/día | B20: =AVERAGE('Datos Crudos'!E4:E6) -> 50 | C20: El sistema debe soportar mínimo 50 transacciones diarias sin degradarse
A21: Máximo de ventas/día | B21: =MAX('Datos Crudos'!E4:E6) -> 50 | C21: Pico de carga: diseñar para al menos este volumen
A22: Mínimo de ventas/día | B22: =MIN('Datos Crudos'!E4:E6) -> 50 | C22: Incluso en día lento, el sistema debe estar disponible
A23: Total estimado mensual | B23: =AVERAGE('Datos Crudos'!E4:E6)*30 -> 1500 | C23: Base para planear capacidad de almacenamiento
A24: Tiempo promedio atención | B24: =AVERAGE('Datos Crudos'!G4:G6) -> 3.6666667 | C24: El sistema debe reducir este tiempo en al menos un 50%

Sheet Gráficas
A1: HOJA 3: Gráficas de Análisis — Supermercado La Esquina
A3: Funcionalidad | B3: Frecuencia | D3: Comodidad con tecnología | E3: Frecuencia
A4: Registro de ventas | B4: 3 | D4: Muy cómodo | E4: 3
A5: Control de inventario | B5: 2 | D5: Cómodo | E5: 3
A6: Ver precios en pantalla | B6: 2 | D6: Poco cómodo | E6: 2
A7: Pago con tarjeta | B7: 1
A9: Opinión Facturación | B9: Frecuencia
A10: Sí | B10: 4
A11: No | B11: 1
A12: No sé / No importa | B12: 2

Sheet Matriz de Priorización
A1: HOJA 4: Matriz de Priorización de Requisitos — Supermercado La Esquina
A2: Escala de valoración: 1 = Bajo | 2 = Medio | 3 = Alto | Puntaje Total = Importancia × Urgencia × Viabilidad
A3: ID | B3: Requisito / Funcionalidad | C3: Importancia (1-3) | D3: Urgencia (1-3) | E3: Viabilidad (1-3) | F3: Puntaje Total | G3: Prioridad | H3: Módulo
A4: RF-01 | B4: Registrar ventas con productos, cantidad y precio | C4: 3 | D4: 3 | E4: 3 | F4: =C4*D4*E4 -> 27 | G4: Crítica | H4: Ventas
A5: RF-02 | B5: Calcular total y cambio automáticamente | C5: 3 | D5: 3 | E5: 3 | F5: =C5*D5*E5 -> 27 | G5: Crítica | H5: Ventas
A6: RF-03 | B6: Búsqueda rápida de productos por nombre/código | C6: 3 | D6: 3 | E6: 2 | F6: =C6*D6*E6 -> 18 | G6: Crítica | H6: Ventas
A7: RF-04 | B7: Control de inventario con stock actualizado | C7: 3 | D7: 3 | E7: 3 | F7: =C7*D7*E7 -> 27 | G7: Crítica | H7: Inventario
A8: RF-05 | B8: Alertas de stock mínimo (producto por agotarse) | C8: 3 | D8: 2 | E8: 3 | F8: =C8*D8*E8 -> 18 | G8: Crítica | H8: Inventario
A9: RF-06 | B9: Registrar entradas de mercancía (compras) | C9: 2 | D9: 2 | E9: 3 | F9: =C9*D9*E9 -> 12 | G9: Alta | H9: Inventario
A10: RF-07 | B10: Gestión de proveedores con datos de contacto | C10: 2 | D10: 2 | E10: 2 | F10: =C10*D10*E10 -> 8 | G10: Media | H10: Proveedores
A11: RF-08 | B11: Historial de pedidos a proveedores | C11: 2 | D11: 1 | E11: 2 | F11: =C11*D11*E11 -> 4 | G11: Baja | H11: Proveedores
A12: RF-09 | B12: Reporte de ventas diarias / mensuales | C12: 3 | D12: 2 | E12: 2 | F12: =C12*D12*E12 -> 12 | G12: Alta | H12: Reportes
A13: RF-10 | B13: Identificar los productos más vendidos | C13: 2 | D13: 1 | E13: 2 | F13: =C13*D13*E13 -> 4 | G13: Baja | H13: Reportes
A14: RNF-01 | B14: Interfaz sencilla (usuarios con baja experiencia digital) | C14: 3 | D14: 3 | E14: 3 | F14: =C14*D14*E14 -> 27 | G14: Crítica | H14: Usabilidad
A15: RNF-02 | B15: Funcionar sin internet (modo offline) | C15: 3 | D15: 3 | E15: 2 | F15: =C15*D15*E15 -> 18 | G15: Crítica | H15: Infraestructura
